Metadata-Version: 2.1
Name: streamlit-df
Version: 1.25
Summary: A faster way to build and share data apps
Home-page: https://streamlit.io
Author: Snowflake Inc
Author-email: hello@streamlit.io
License: Apache License 2.0
Project-URL: Source Code, https://github.com/streamlit/streamlit
Project-URL: Bug Tracker, https://github.com/streamlit/streamlit/issues
Project-URL: Release notes, https://docs.streamlit.io/library/changelog
Project-URL: Documentation, https://docs.streamlit.io/
Project-URL: Community, https://discuss.streamlit.io/
Project-URL: Twitter, https://twitter.com/streamlit
Classifier: Development Status :: 5 - Production/Stable
Classifier: Environment :: Console
Classifier: Environment :: Web Environment
Classifier: Intended Audience :: Developers
Classifier: Intended Audience :: Science/Research
Classifier: License :: OSI Approved :: Apache Software License
Classifier: Programming Language :: Python :: 3.8
Classifier: Programming Language :: Python :: 3.9
Classifier: Programming Language :: Python :: 3.10
Classifier: Programming Language :: Python :: 3.11
Classifier: Topic :: Database :: Front-Ends
Classifier: Topic :: Office/Business :: Financial :: Spreadsheet
Classifier: Topic :: Scientific/Engineering :: Information Analysis
Classifier: Topic :: Scientific/Engineering :: Visualization
Classifier: Topic :: Software Development :: Libraries :: Application Frameworks
Classifier: Topic :: Software Development :: Widget Sets
Requires-Python: >=3.8, !=3.9.7
Requires-Dist: altair <6,>=4.0
Requires-Dist: blinker <2,>=1.0.0
Requires-Dist: cachetools <6,>=4.0
Requires-Dist: click <9,>=7.0
Requires-Dist: importlib-metadata <7,>=1.4
Requires-Dist: numpy <2,>=1.19.3
Requires-Dist: packaging <24,>=16.8
Requires-Dist: pandas <3,>=1.3.0
Requires-Dist: pillow <11,>=7.1.0
Requires-Dist: protobuf <5,>=3.20
Requires-Dist: pyarrow >=6.0
Requires-Dist: python-dateutil <3,>=2.7.3
Requires-Dist: requests <3,>=2.27
Requires-Dist: rich <14,>=10.14.0
Requires-Dist: tenacity <9,>=8.1.0
Requires-Dist: toml <2,>=0.10.1
Requires-Dist: typing-extensions <5,>=4.3.0
Requires-Dist: tzlocal <6,>=1.1
Requires-Dist: validators <1,>=0.2
Requires-Dist: gitpython !=3.1.19,<4,>=3.0.7
Requires-Dist: pydeck <1,>=0.8.0b4
Requires-Dist: tornado <7,>=6.0.3
Requires-Dist: watchdog >=2.1.5 ; platform_system != "Darwin"
Provides-Extra: snowflake
Requires-Dist: snowflake-snowpark-python >=0.9.0 ; (python_version == "3.8") and extra == 'snowflake'
Requires-Dist: snowflake-connector-python >=2.8.0 ; (python_version == "3.8") and extra == 'snowflake'
